vxformsapi/API.py
vxformsapi/__init__.py
vxformsapi-0.3.1.dist-info/LICENSE
vxformsapi-0.3.1.dist-info/METADATA
vxformsapi-0.3.1.dist-info/WHEEL
vxformsapi-0.3.1.dist-info/top_level.txt
vxformsapi-0.3.1.dist-info/RECORD
