Metadata-Version: 2.1
Name: vxformsapi
Version: 0.3.1
Summary: API for the VxForms Material Database.
Home-page: https://github.com/M9-Calibre/BD_API_Materials
Author: Afonso Campos <afonso.campos@ua.pt>, Lucius Vinicius <luciusviniciusf@ua.pt>
Classifier: Development Status :: 2 - Pre-Alpha
Classifier: Intended Audience :: Developers
Classifier: Topic :: Software Development :: Libraries
Classifier: License :: OSI Approved :: MIT License
Classifier: Programming Language :: Python :: 3.10
License-File: LICENSE
Requires-Dist: requests
Requires-Dist: pandas
